{"name":"Vijaykr.GitHub.io","tagline":"","body":"<!DOCTYPE html PUBLIC \"-//W3C//DTD XHTML 1.0 Transitional//EN\" \"http://www.w3.org/TR/xhtml1/DTD/xhtml1-transitional.dtd\">\r\n<html xmlns=\"http://www.w3.org/1999/xhtml\">\r\n<head>\r\n    <title></title>\r\n    <style type=\"text/css\">\r\n        body\r\n        {\r\n            font-family: Arial;\r\n            font-size: 10pt;\r\n        }\r\n    </style>\r\n</head>\r\n<body>\r\n    <script type=\"text/javascript\" src=\"http://maps.googleapis.com/maps/api/js?sensor=false&libraries=places\"></script>\r\n    <script type=\"text/javascript\">\r\n        var source, destination;\r\n        var directionsDisplay;\r\n        var directionsService = new google.maps.DirectionsService();\r\n        google.maps.event.addDomListener(window, 'load', function () {\r\n            new google.maps.places.SearchBox(document.getElementById('txtSource'));\r\n            new google.maps.places.SearchBox(document.getElementById('txtDestination'));\r\n            directionsDisplay = new google.maps.DirectionsRenderer({ 'draggable': true });\r\nvar mumbai = new google.maps.LatLng(13.0827, 80.2707);\r\n            var mapOptions = {\r\n                zoom: 7,\r\n                center: mumbai\r\n            };\r\n            map = new google.maps.Map(document.getElementById('dvMap'), mapOptions);\r\n            directionsDisplay.setMap(map);\r\n        });\r\n\r\n        function GetRoute() {\r\n            var mumbai = new google.maps.LatLng(13.0827, 80.2707);\r\n            var mapOptions = {\r\n                zoom: 7,\r\n                center: mumbai\r\n            };\r\n            map = new google.maps.Map(document.getElementById('dvMap'), mapOptions);\r\n            directionsDisplay.setMap(map);\r\n            directionsDisplay.setPanel(document.getElementById('dvPanel'));\r\n\r\n            //*********DIRECTIONS AND ROUTE**********************//\r\n            source = document.getElementById(\"txtSource\").value;\r\n            destination = document.getElementById(\"txtDestination\").value;\r\n\r\n            var request = {\r\n                origin: source,\r\n                destination: destination,\r\n                travelMode: google.maps.TravelMode.DRIVING\r\n            };\r\n            directionsService.route(request, function (response, status) {\r\n                if (status == google.maps.DirectionsStatus.OK) {\r\n                    directionsDisplay.setDirections(response);\r\n                }\r\n            });\r\n\r\n            //*********DISTANCE AND DURATION**********************//\r\n            var service = new google.maps.DistanceMatrixService();\r\n            service.getDistanceMatrix({\r\n                origins: [source],\r\n                destinations: [destination],\r\n                travelMode: google.maps.TravelMode.DRIVING,\r\n                unitSystem: google.maps.UnitSystem.METRIC,\r\n                avoidHighways: false,\r\n                avoidTolls: false\r\n            }, function (response, status) {\r\n                if (status == google.maps.DistanceMatrixStatus.OK && response.rows[0].elements[0].status != \"ZERO_RESULTS\") {\r\n                    var distance = response.rows[0].elements[0].distance.text;\r\n                    var duration = response.rows[0].elements[0].duration.text;\r\n                    var dvDistance = document.getElementById(\"dvDistance\");\r\n                    dvDistance.innerHTML = \"\";\r\n                    dvDistance.innerHTML += \"Distance: \" + distance + \"<br />\";\r\n                    dvDistance.innerHTML += \"Duration:\" + duration;\r\n\r\n                } else {\r\n                    alert(\"Unable to find the distance via road.\");\r\n                }\r\n            });\r\n        }\r\n    </script>\r\n    <table border=\"0\" cellpadding=\"0\" cellspacing=\"3\">\r\n        <tr>\r\n            <td colspan=\"2\">\r\n                Source:\r\n                <input type=\"text\" id=\"txtSource\" value=\" \" style=\"width: 200px\" />\r\n                &nbsp; Destination:\r\n                <input type=\"text\" id=\"txtDestination\" value=\" \" style=\"width: 200px\" />\r\n                <br />\r\n                <input type=\"button\" value=\"Get Route\" onclick=\"GetRoute()\" />\r\n                <hr />\r\n            </td>\r\n        </tr>\r\n        <tr>\r\n            <td colspan=\"2\">\r\n                <div id=\"dvDistance\">\r\n                </div>\r\n            </td>\r\n        </tr>\r\n        <tr>\r\n            <td>\r\n                <div id=\"dvMap\" style=\"width: 500px; height: 500px\">\r\n                </div>\r\n            </td>\r\n            <td>\r\n                <div id=\"dvPanel\" style=\"width: 500px; height: 500px\">\r\n                </div>\r\n            </td>\r\n        </tr>\r\n    </table>\r\n    <br />\r\n</body>\r\n</html>\r\n","google":"","note":"Don't delete this file! It's used internally to help with page regeneration."}